Metadata-Version: 2.1
Name: pythonguts
Version: 0.1.0
Summary: Tool aimed at python code correction that allows to automatically find and replace function definition
Home-page: https://github.com/tierra-colada/pythonguts
Author: kerim khemrev
Author-email: tierracolada@gmail.com
License: MIT
Download-URL: https://github.com/tierra-colada/pythonguts/archive/refs/tags/v0.1.0.tar.gz
Keywords: py-parser python-parser py-editor python-editor py-generator python-generator
Platform: UNKNOWN
Classifier: Development Status :: 5 - Production/Stable
Classifier: Environment :: Console
Classifier: Intended Audience :: Developers
Classifier: Topic :: Software Development :: Build Tools
Classifier: Topic :: Software Development :: Code Generators
Classifier: License :: OSI Approved :: MIT License
Classifier: Programming Language :: Python :: 3.6
Classifier: Programming Language :: Python :: 3.7
Classifier: Programming Language :: Python :: 3.8
Classifier: Programming Language :: Python :: 3.9
Requires-Python: >=3
License-File: LICENSE
